Kapok-0.2.1.dist-info/DESCRIPTION.rst
Kapok-0.2.1.dist-info/METADATA
Kapok-0.2.1.dist-info/RECORD
Kapok-0.2.1.dist-info/WHEEL
Kapok-0.2.1.dist-info/metadata.json
Kapok-0.2.1.dist-info/top_level.txt
kapok/__init__.py
kapok/cohopt.py
kapok/cohoptc.cp35-win_amd64.pyd
kapok/cohoptp.py
kapok/geo.py
kapok/kapok.py
kapok/region.py
kapok/rvog.py
kapok/rvogc.cp35-win_amd64.pyd
kapok/rvogp.py
kapok/sinc.py
kapok/topo.py
kapok/uavsar.py
kapok/uavsarc.cp35-win_amd64.pyd
kapok/uavsarp.py
kapok/vis.py
kapok/lib/__init__.py
kapok/lib/coords.py
kapok/lib/interp.py
kapok/lib/matrix.py
kapok/lib/mb.py
kapok/lib/slope.py
kapok/lib/win.py
