Metadata-Version: 2.0
Name: Kapok
Version: 0.2.1
Summary: A Python library for PolInSAR forest height estimation using UAVSAR data.
Home-page: https://github.com/mdenbina/kapok
Author: Michael Denbina
Author-email: michael.w.denbina@jpl.nasa.gov
License: GPLv3+
Keywords: radar remotesensing ecology forestry biomass polinsar polarimetry
Platform: UNKNOWN
Classifier: Development Status :: 3 - Alpha
Classifier: Intended Audience :: Science/Research
Classifier: Topic :: Scientific/Engineering
Classifier: License :: OSI Approved :: GNU General Public License v3 or later (GPLv3+)
Classifier: Programming Language :: Python :: 3 :: Only
Requires-Dist: cython
Requires-Dist: gdal
Requires-Dist: h5py
Requires-Dist: matplotlib
Requires-Dist: numpy
Requires-Dist: pyresample
Requires-Dist: scipy
